{"name":"loginCheckAndValidationLockedOutUser","id":"loginTests.loginTestsParameterized:loginCheckAndValidationLockedOutUser","testCaseName":"loginTests.loginTestsParameterized","testSteps":[{"number":1,"description":"Parameterized Test run with array of username and password - lockedOut/Empty Users ","duration":3685,"startTime":"2021-05-27T17:00:28.743548900+03:00[Europe/Athens]","result":"SUCCESS","precondition":false,"level":0,"children":[{"number":2,"description":"Navigate to the url https://www.saucedemo.com/","duration":3040,"startTime":"2021-05-27T17:00:05.041252600+03:00[Europe/Athens]","screenshots":[{"screenshot":"3b60fc8d4fa60f42200c670c754fe551eefec424bb0dfd3c3594a686f2a18d0f.png","timeStamp":1622124008080}],"result":"SUCCESS","precondition":false,"level":1},{"number":3,"description":"Enter credentials in boxes with username locked_out_user and password secret_sauce","duration":452,"startTime":"2021-05-27T17:00:08.085960900+03:00[Europe/Athens]","screenshots":[{"screenshot":"0e21df8ad1cd8fb9eccb7311897f09334d61a1a529366644662248dd03c47088.png","timeStamp":1622124008538}],"result":"SUCCESS","precondition":false,"level":1},{"number":4,"description":"Expected: PARAMETRIZED RUN, error message check! - Empty/LockedOut user with EmptyLockedOutErrorMessage \u003d Epic sadface: Sorry, this user has been locked out.","duration":193,"startTime":"2021-05-27T17:00:08.540206800+03:00[Europe/Athens]","screenshots":[{"screenshot":"0e21df8ad1cd8fb9eccb7311897f09334d61a1a529366644662248dd03c47088.png","timeStamp":1622124008733}],"result":"SUCCESS","precondition":false,"level":1}]},{"number":5,"description":"Parameterized Test run with array of username and password - lockedOut/Empty Users ","duration":2450,"startTime":"2021-05-27T17:00:28.743548900+03:00[Europe/Athens]","result":"SUCCESS","precondition":false,"level":0,"children":[{"number":6,"description":"Navigate to the url https://www.saucedemo.com/","duration":1992,"startTime":"2021-05-27T17:00:09.548202500+03:00[Europe/Athens]","screenshots":[{"screenshot":"3b60fc8d4fa60f42200c670c754fe551eefec424bb0dfd3c3594a686f2a18d0f.png","timeStamp":1622124011540}],"result":"SUCCESS","precondition":false,"level":1},{"number":7,"description":"Enter credentials in boxes with username  and password ","duration":415,"startTime":"2021-05-27T17:00:11.541281900+03:00[Europe/Athens]","screenshots":[{"screenshot":"06aec2f4757c5c710efc922f84bb54894f90c06f83b2a99b2952457acd230788.png","timeStamp":1622124011956}],"result":"SUCCESS","precondition":false,"level":1},{"number":8,"description":"Expected: PARAMETRIZED RUN, error message check! - Empty/LockedOut user with EmptyLockedOutErrorMessage \u003d Epic sadface: Username is required","duration":43,"startTime":"2021-05-27T17:00:11.961797800+03:00[Europe/Athens]","screenshots":[{"screenshot":"06aec2f4757c5c710efc922f84bb54894f90c06f83b2a99b2952457acd230788.png","timeStamp":1622124012005}],"result":"SUCCESS","precondition":false,"level":1}]},{"number":9,"description":"Parameterized Test run with array of username and password - lockedOut/Empty Users ","duration":7088,"startTime":"2021-05-27T17:00:28.743548900+03:00[Europe/Athens]","exception":{"errorType":"org.openqa.selenium.NoSuchElementException","message":"Timed out after 2 seconds. Element not found\nFor documentation on this error, please visit: https://www.seleniumhq.org/exceptions/no_such_element.html\nBuild info: version: \u00273.141.59\u0027, revision: \u0027e82be7d358\u0027, time: \u00272018-11-14T08:17:03\u0027\nSystem info: host: \u0027CJ003963LT\u0027, ip: \u002710.83.111.92\u0027, os.name: \u0027Windows 10\u0027, os.arch: \u0027amd64\u0027, os.version: \u002710.0\u0027, java.version: \u002711.0.10\u0027\nDriver info: driver.version: unknown\nFor documentation on this error, please visit: https://www.seleniumhq.org/exceptions/no_such_element.html\nBuild info: version: \u00273.141.59\u0027, revision: \u0027e82be7d358\u0027, time: \u00272018-11-14T08:17:03\u0027\nSystem info: host: \u0027CJ003963LT\u0027, ip: \u002710.83.111.92\u0027, os.name: \u0027Windows 10\u0027, os.arch: \u0027amd64\u0027, os.version: \u002710.0\u0027, java.version: \u002711.0.10\u0027\nDriver info: driver.version: unknown\nFor documentation on this error, please visit: https://www.seleniumhq.org/exceptions/no_such_element.html\nBuild info: version: \u00273.141.59\u0027, revision: \u0027e82be7d358\u0027, time: \u00272018-11-14T08:17:03\u0027\nSystem info: host: \u0027CJ003963LT\u0027, ip: \u002710.83.111.92\u0027, os.name: \u0027Windows 10\u0027, os.arch: \u0027amd64\u0027, os.version: \u002710.0\u0027, java.version: \u002711.0.10\u0027\nDriver info: driver.version: unknown","stackTrace":[{"classLoaderName":"app","declaringClass":"pageObjects.LoginPageObject","methodName":"getEmptyAndLockedOutErrorMessage","fileName":"LoginPageObject.java","lineNumber":32,"format":1},{"classLoaderName":"app","declaringClass":"steps.LoginSteps","methodName":"emptyAndLockedOutUserErrorCheck","fileName":"LoginSteps.java","lineNumber":36,"format":1},{"classLoaderName":"app","declaringClass":"loginTests.loginTestsParameterized","methodName":"loginCheckAndValidationLockedOutUser","fileName":"loginTestsParameterized.java","lineNumber":58,"format":1}]},"result":"ERROR","precondition":false,"level":0,"children":[{"number":10,"description":"Navigate to the url https://www.saucedemo.com/","duration":1985,"startTime":"2021-05-27T17:00:12.767697+03:00[Europe/Athens]","screenshots":[{"screenshot":"3b60fc8d4fa60f42200c670c754fe551eefec424bb0dfd3c3594a686f2a18d0f.png","timeStamp":1622124014752}],"result":"SUCCESS","precondition":false,"level":1},{"number":11,"description":"Enter credentials in boxes with username standard_user and password secret_sauce","duration":715,"startTime":"2021-05-27T17:00:14.753133300+03:00[Europe/Athens]","screenshots":[{"screenshot":"a84ea832def3966a20f67f525f18cd9c546f037b087c6cdd154bba0efd331410.png","timeStamp":1622124015468}],"result":"SUCCESS","precondition":false,"level":1},{"number":12,"description":"Expected: PARAMETRIZED RUN, error message check! - Empty/LockedOut user with EmptyLockedOutErrorMessage \u003d Epic sadface: Username is required","duration":4388,"startTime":"2021-05-27T17:00:15.468242200+03:00[Europe/Athens]","screenshots":[{"screenshot":"9e828bc7ad712496ee9ddea0db55ff1599a8ecec47b4367544c7ad5e2ba74d35.png","htmlSource":"pagesource2677070867451034210.html.txt","timeStamp":1622124019853}],"exception":{"errorType":"org.openqa.selenium.NoSuchElementException","message":"Timed out after 2 seconds. Element not found\nFor documentation on this error, please visit: https://www.seleniumhq.org/exceptions/no_such_element.html\nBuild info: version: \u00273.141.59\u0027, revision: \u0027e82be7d358\u0027, time: \u00272018-11-14T08:17:03\u0027\nSystem info: host: \u0027CJ003963LT\u0027, ip: \u002710.83.111.92\u0027, os.name: \u0027Windows 10\u0027, os.arch: \u0027amd64\u0027, os.version: \u002710.0\u0027, java.version: \u002711.0.10\u0027\nDriver info: driver.version: unknown","stackTrace":[{"classLoaderName":"app","declaringClass":"pageObjects.LoginPageObject","methodName":"getEmptyAndLockedOutErrorMessage","fileName":"LoginPageObject.java","lineNumber":32,"format":1},{"classLoaderName":"app","declaringClass":"steps.LoginSteps","methodName":"emptyAndLockedOutUserErrorCheck","fileName":"LoginSteps.java","lineNumber":36,"format":1},{"classLoaderName":"app","declaringClass":"loginTests.loginTestsParameterized","methodName":"loginCheckAndValidationLockedOutUser","fileName":"loginTestsParameterized.java","lineNumber":58,"format":1}]},"result":"ERROR","precondition":false,"level":1}]},{"number":13,"description":"Parameterized Test run with array of username and password - lockedOut/Empty Users ","duration":3526,"startTime":"2021-05-27T17:00:28.744511600+03:00[Europe/Athens]","result":"SUCCESS","precondition":false,"level":0,"children":[{"number":14,"description":"Navigate to the url https://www.saucedemo.com/","duration":3113,"startTime":"2021-05-27T17:00:20.744990+03:00[Europe/Athens]","screenshots":[{"screenshot":"3b60fc8d4fa60f42200c670c754fe551eefec424bb0dfd3c3594a686f2a18d0f.png","timeStamp":1622124023858}],"result":"SUCCESS","precondition":false,"level":1},{"number":15,"description":"Enter credentials in boxes with username  and password ","duration":370,"startTime":"2021-05-27T17:00:23.859769600+03:00[Europe/Athens]","screenshots":[{"screenshot":"06aec2f4757c5c710efc922f84bb54894f90c06f83b2a99b2952457acd230788.png","timeStamp":1622124024229}],"result":"SUCCESS","precondition":false,"level":1},{"number":16,"description":"Expected: PARAMETRIZED RUN, error message check! - Empty/LockedOut user with EmptyLockedOutErrorMessage \u003d Epic sadface: Username is required","duration":43,"startTime":"2021-05-27T17:00:24.230777800+03:00[Europe/Athens]","screenshots":[{"screenshot":"06aec2f4757c5c710efc922f84bb54894f90c06f83b2a99b2952457acd230788.png","timeStamp":1622124024274}],"result":"SUCCESS","precondition":false,"level":1}]},{"number":17,"description":"Parameterized Test run with array of username and password - lockedOut/Empty Users ","duration":2571,"startTime":"2021-05-27T17:00:28.744511600+03:00[Europe/Athens]","result":"SUCCESS","precondition":false,"level":0,"children":[{"number":18,"description":"Navigate to the url https://www.saucedemo.com/","duration":2143,"startTime":"2021-05-27T17:00:25.463694700+03:00[Europe/Athens]","screenshots":[{"screenshot":"3b60fc8d4fa60f42200c670c754fe551eefec424bb0dfd3c3594a686f2a18d0f.png","timeStamp":1622124027607}],"result":"SUCCESS","precondition":false,"level":1},{"number":19,"description":"Enter credentials in boxes with username  and password ","duration":387,"startTime":"2021-05-27T17:00:27.608107900+03:00[Europe/Athens]","screenshots":[{"screenshot":"06aec2f4757c5c710efc922f84bb54894f90c06f83b2a99b2952457acd230788.png","timeStamp":1622124027996}],"result":"SUCCESS","precondition":false,"level":1},{"number":20,"description":"Expected: PARAMETRIZED RUN, error message check! - Empty/LockedOut user with EmptyLockedOutErrorMessage \u003d Epic sadface: Username is required","duration":41,"startTime":"2021-05-27T17:00:27.997067600+03:00[Europe/Athens]","screenshots":[{"screenshot":"06aec2f4757c5c710efc922f84bb54894f90c06f83b2a99b2952457acd230788.png","timeStamp":1622124028038}],"result":"SUCCESS","precondition":false,"level":1}]}],"userStory":{"id":"loginTests.loginTestsParameterized","storyName":"Login tests parameterized","storyClassName":"loginTests.loginTestsParameterized","path":"loginTests","type":"story"},"featureTag":{"name":"Login tests/Login tests parameterized","type":"story","displayName":"Login tests/Login tests parameterized"},"title":"Parameterized Test run with array of username and password - lockedOut/Empty Users","tags":[{"name":"Login tests/Login tests parameterized","type":"story","displayName":"Login tests/Login tests parameterized"}],"startTime":"2021-05-27T17:00:28.743548900+03:00[Europe/Athens]","duration":0,"isManualTestingUpToDate":false,"dataTable":{"headers":["Parameter 1","Parameter 2","Parameter 3"],"rows":[{"values":["locked_out_user","secret_sauce","Epic sadface: Sorry, this user has been locked out."],"result":"SUCCESS"},{"values":["","","Epic sadface: Username is required"],"result":"SUCCESS"},{"values":["standard_user","secret_sauce","Epic sadface: Username is required"],"result":"ERROR"},{"values":["","","Epic sadface: Username is required"],"result":"SUCCESS"},{"values":["","","Epic sadface: Username is required"],"result":"SUCCESS"}],"predefinedRows":false,"dataSetDescriptors":[{"startRow":0,"rowCount":0}]},"manual":false,"result":"ERROR"}